srrp/ContactDiscontinuity.py
srrp/EquationOfState.py
srrp/Rarefaction.py
srrp/Shock.py
srrp/Solver.py
srrp/State.py
srrp/Util.py
srrp/Wavefan.py
srrp/__init__.py
tests/__init__.py
srrp-1.0.1.dist-info/LICENSE
srrp-1.0.1.dist-info/METADATA
srrp-1.0.1.dist-info/WHEEL
srrp-1.0.1.dist-info/top_level.txt
srrp-1.0.1.dist-info/RECORD
