Metadata-Version: 2.1
Name: srrp
Version: 1.0.1
Summary: An exact solver for special relativistic riemann problems
Home-page: https://github.com/cxkoda/srrp
Author: David Huber
Author-email: dave@yomi.eu
License: UNKNOWN
Platform: UNKNOWN
Classifier: Programming Language :: Python :: 3
Classifier: License :: OSI Approved :: GNU General Public License v3 (GPLv3)
Classifier: Operating System :: OS Independent
Requires-Python: >=3.6
Requires-Dist: scipy (>=1.4.0)
Requires-Dist: numpy (>=1.17.0)
